clickdc.py
clickdc-0.1.1.dist-info/LICENSE
clickdc-0.1.1.dist-info/METADATA
clickdc-0.1.1.dist-info/WHEEL
clickdc-0.1.1.dist-info/top_level.txt
clickdc-0.1.1.dist-info/RECORD
