Metadata-Version: 2.1
Name: clickdc
Version: 0.1.1
Summary: Manage click arguments using python dataclass
Author: Kamil Cukrowski
License: MIT
Project-URL: homepage, https://github.com/Kamilcuk/clickdc
Project-URL: repository, https://github.com/Kamilcuk/clickdc
Project-URL: documentation, https://github.com/Kamilcuk/clickdc
License-File: LICENSE
Requires-Dist: typing-extensions
Requires-Dist: click
Provides-Extra: test
Requires-Dist: pytest; extra == "test"
Requires-Dist: pydantic; extra == "test"
Requires-Dist: pyright[nodejs]; extra == "test"
